{
  "external_id": "ESP_025753_1755_40960_46080_10240_15169.png",
  "observation_id": "ESP_025753_1755",
  "resolution": 0.5,
  "original_resolution": 0.5,
  "tile_bbox": "POLYGON ((2990 4784, 2990 5083, 2691 5083, 2691 4784, 2990 4784))",
  "subframe_classifications": [
    {
      "labeler": "automated",
      "classification": [
        {
          "feature_schema_id": "automated",
          "frost_present": "false"
        },
        {
          "feature_schema_id": "automated",
          "confidence": "high_90"
        }
      ]
    }
  ],
  "annotations": [],
  "class": "background",
  "image_coords": [
    45744,
    46043,
    12931,
    13230
  ]
}